simtwin/__init__.py
simtwin/broker.py
simtwin/exceptions.py
simtwin/geometry.py
simtwin/mesh.py
simtwin/server.py
simtwin/simtwin_base_classes.py
simtwin/simulation.py
simtwin/utils.py
simtwin-0.0.44.dist-info/LICENSE
simtwin-0.0.44.dist-info/METADATA
simtwin-0.0.44.dist-info/WHEEL
simtwin-0.0.44.dist-info/top_level.txt
simtwin-0.0.44.dist-info/RECORD
