Metadata-Version: 2.1
Name: simtwin
Version: 0.0.44
Summary: Simtwin allows to exchange simulation data with a remote simulation server by automatically crating twins of the users created objects on the server.
Author-email: Henrik Stromberg <henrik@askdrq.com>
License: Copyright (c) 2023 Henrik Stromberg
Project-URL: homepage, https://askdrq.com
License-File: LICENSE
Requires-Dist: gmsh >=4.10.5
Requires-Dist: matplotlib >=3.6.1
Requires-Dist: numpy >=1.23.3
Requires-Dist: rootpath >=0.1.1
